{
  "nodes": [
    {
      "group": 1,
      "name": "Henderson-Begg, Liselott",
      "url": null,
      "gender": "male",
      "tatelink": "http://www.tate.org.uk/art/artists/liselott-henderson-begg-1270",
      "id": "Artist",
      "size": 30
    },
    {
      "group": 1,
      "name": "untitled",
      "url": "",
      "gender": null,
      "tatelink": "http://www.tate.org.uk/art/artworks/henderson-begg-untitled-p06248",
      "id": "5956",
      "size": 50
    }
  ],
  "links": [
    {
      "source": "Artist",
      "target": "5956",
      "value": 1
    }
  ]
}