{
  "nodes": [
    {
      "group": 1,
      "name": "Arnald, George",
      "url": null,
      "gender": "male",
      "tatelink": "http://www.tate.org.uk/art/artists/george-arnald-13",
      "id": "Artist",
      "size": 30
    },
    {
      "group": 1,
      "name": "view on the ouse at york",
      "url": "http://www.tate.org.uk/art/images/work/N/N01/N01156_8.jpg",
      "gender": null,
      "tatelink": "http://www.tate.org.uk/art/artworks/arnald-view-on-the-ouse-at-york-n01156",
      "id": "588",
      "size": 50
    }
  ],
  "links": [
    {
      "source": "Artist",
      "target": "588",
      "value": 1
    }
  ]
}