{
  "nodes": [
    {
      "group": 1,
      "name": "Wylie, Rose",
      "url": null,
      "gender": "female",
      "tatelink": "http://www.tate.org.uk/art/artists/rose-wylie-17422",
      "id": "Artist",
      "size": 30
    },
    {
      "group": 1,
      "name": "pin up and porn queen jigsaw",
      "url": "",
      "gender": null,
      "tatelink": "http://www.tate.org.uk/art/artworks/wylie-pin-up-and-porn-queen-jigsaw-t13784",
      "id": "126592",
      "size": 50
    }
  ],
  "links": [
    {
      "source": "Artist",
      "target": "126592",
      "value": 1
    }
  ]
}